colortool.py
colortool-0.6.0.dist-info/METADATA
colortool-0.6.0.dist-info/WHEEL
colortool-0.6.0.dist-info/top_level.txt
colortool-0.6.0.dist-info/RECORD
