Metadata-Version: 2.1
Name: colortool
Version: 0.6.0
Summary: set of tools to work with different color formats
Author-email: Alexander Rodionov <tandav@tandav.me>
Project-URL: source, https://github.com/tandav/colortool
Project-URL: issues, https://gitlab.tandav.me/tandav/notes/-/issues?label_name%5B%5D=colortool
Project-URL: release notes, https://github.com/tandav/colortool/releases
Requires-Python: >=3.8
Provides-Extra: dev
Requires-Dist: bumpver ; extra == 'dev'
Requires-Dist: pre-commit ; extra == 'dev'
Requires-Dist: pytest ; extra == 'dev'
